pathorstr/__init__.py
pathorstr/_pathorstr.py
pathorstr-2025.7.14.0.dist-info/METADATA
pathorstr-2025.7.14.0.dist-info/WHEEL
pathorstr-2025.7.14.0.dist-info/top_level.txt
pathorstr-2025.7.14.0.dist-info/RECORD
