Metadata-Version: 2.4
Name: pathorstr
Version: 2025.7.14.0
Summary: Unify Path and str
Author-email: Ann T Ropea <bedhanger@gmx.de>
License-Expression: MIT
Project-URL: Homepage, https://gitlab.com/bedhanger/mwe/-/tree/master/python/pathorstr
